{"count":8601,"results":[{"listing_id":974497164,"state":"active","user_id":32964492,"category_id":null,"title":"To My Amazing Son - Love From Mom Blanket, Gift For Kids Adults Families And Friends","description":"To My Amazing Son - Love From Mom Blanket, Gift For Kids Adults Families And Friends\n\n\nThere Are 3 Size To Choose: 30&quot;x40&quot;, 50&quot;x60&quot;, 80&quot;x60&quot;(Queen Size)\n\nIf You Need Order A Custom Blanket By Your Own Design, Pls Contact Us !! \n\nFLEECE BLANKET: Blanket brings you a breathable and lightweight feeling than regular cotton blankets. Keeping your body warm while providing you a soft and gentle touching with great quality and superior softness.Suitable for use on the couch or bed, a chair, in the car, or you can use it on a picnic or camping as it is lightweight and packs very small. A perfect gift choice for Valentine\u2019s Day, Father\u2019s Day, Mother\u2019s Day, Christmas, New Year, and memorial days.Machine washable in warm or cold water, easy to store, wrinkle \u2013 resistant. Maintains its color and does not shed. Full color all over print; Prints edge to edge on one side \n\nCare: Machine wash separately in cold water; Tumble dry on low heat \n\nMINKY BLANKET: Minky blanket is an incredibly soft, luxurious blanket that provides a lot of warmth yet lacks the bulk that comes with certain types of blankets such as those made from wool. They&#39;re the type of blankets you can put anywhere in your house as a throw; over beds, the backs of couches and chairs Full color all over print; Prints edge to edge on one side \n\nCare: Machine wash separately in cold water; Tumble dry on low heat \n\nSHERPA BLANKET: Sherpa Blanket is super soft, fluffy sherpa throw blanket is the perfect gift for yourself and others! Personalized with custom name monogram makes this blanket the ultimate gift for weddings, anniversaries, housewarming, first home purchases, holidays, birthdays and more! This is the perfect gift for every occasion, any time of year! Personalized gifts take gift giving to the next level. Full color all over print; Prints edge to edge on one side \n\nCare: Machine wash separately in cold water; Tumble dry on low heat \n\nWE DO NOT ACCEPT CANCELATION ( please don&#39;t place an order if you plan on canceling, since we won&#39;t cancel the order)\n\n***Thank you so much for your purchase and we hope you enjoy these creative resources!","creation_tsz":1616731338,"ending_tsz":1627272138,"original_creation_tsz":1616731338,"last_modified_tsz":1618549639,"price":"35.99","currency_code":"USD","quantity":999,"sku":["Thuong96"],"tags":["blanket quotes","cozy blanket","soft blanket adult","soft blanket kid","family blanket","birthday gifts ideas","lion blanket baby","inspirational quotes","family quotes","family is love","son quotes","mom and son blanket","laugh love live"],"materials":["Fleece","Minky"],"shop_section_id":33143136,"featured_rank":null,"state_tsz":1616731338,"url":"https:\/\/www.etsy.com\/listing\/974497164\/to-my-amazing-son-love-from-mom-blanket?utm_source=thepuddinglistingima&utm_medium=api&utm_campaign=api","views":3,"num_favorers":0,"shipping_template_id":133629972192,"processing_min":3,"processing_max":5,"who_made":"i_did","is_supply":"false","when_made":"made_to_order","item_weight":null,"item_weight_unit":"oz","item_length":null,"item_width":null,"item_height":null,"item_dimensions_unit":"in","is_private":false,"recipient":null,"occasion":null,"style":null,"non_taxable":false,"is_customizable":false,"is_digital":false,"file_data":"","should_auto_renew":true,"language":"en-US","has_variations":true,"taxonomy_id":913,"taxonomy_path":["Home & Living","Bedding","Blankets & Throws"],"used_manufacturer":false,"is_vintage":false},{"listing_id":527869937,"state":"active","user_id":93203511,"category_id":null,"title":"Live, Laugh, Love, Home Decor, Metal Wall Art,Wall Sculpture, Asian, Oriental, Inspirational, Motivational","description":"LIVE, LAUGH, LOVE\n   \n   Oriental, is one of the more popular decorating styles today. With this in mind, we are pleased to make available, as wall hangings, three of the more popular words\u2026.&quot;Live, Laugh, Love&quot;. These pieces will provide that needed focal point in any Oriental-themed room. We sell these as a group of three or they can also be purchased separately. \n\n                                           Quality Craftsmanship\n   \n   Each piece measures 9 inches wide by 11 inches tall with the back plate and characters being cut from 12 gauge steel. We use thicker steel, approximately 1\/8 inch, than our competitors. We feel this provides a more substantial piece with more eye appeal. It is then prepped and painted by hand, then sealed with a UV protected clear coat. Each piece has a welded loop on the back to facilitate hanging.\n\n                                             Options\n   \n   As with all of our pieces these can be custom ordered in any size and colors. Please contact us for pricing on larger sizes.\n\n                                           Custom Design\n  \n    We do not carry a large inventory. We cater to you our Customer, for this reason, we usually cut orders as we receive them. In this way, if you require the piece to be modified (color, special hangers, etc)  then we can accommodate your needs, usually without extra charges.  As a rule, the only extra charge we will make will be for larger sizes\u2026.This requires us to put a  fifteen-day shipping time on the piece. Most of the time we ship sooner rather than later. Contact us for pricing on larger sizes.\n\n   Unless requested by a Customer we do not use clip art or purchased designs. Like our other designs, this is an in-house Copyrighted\u00a9 design. This is an heirloom-quality piece that will be appreciated for generations to come.\n\nNote: This is not a toy. Although we make every effort to make each piece as safe as possible, due to the design there will most likely be sharp edges and sharp points.","creation_tsz":1616730645,"ending_tsz":1627271445,"original_creation_tsz":1493495848,"last_modified_tsz":1617306088,"price":"165.00","currency_code":"USD","quantity":2,"sku":["10023"],"tags":["Japan","Asian","Metal Art","Live Laugh Love","Live","Laugh","Love","China","Japanese","Oriental","Kanji","Home"],"materials":["Steel","Paint"],"shop_section_id":25214784,"featured_rank":null,"state_tsz":1528352169,"url":"https:\/\/www.etsy.com\/listing\/527869937\/live-laugh-love-home-decor-metal-wall?utm_source=thepuddinglistingima&utm_medium=api&utm_campaign=api","views":142,"num_favorers":13,"shipping_template_id":38724975946,"processing_min":10,"processing_max":15,"who_made":"i_did","is_supply":"false","when_made":"2010_2019","item_weight":"112","item_weight_unit":"oz","item_length":"11","item_width":"9","item_height":"6","item_dimensions_unit":"in","is_private":false,"recipient":null,"occasion":null,"style":null,"non_taxable":false,"is_customizable":true,"is_digital":false,"file_data":"","should_auto_renew":true,"language":"en-US","has_variations":false,"taxonomy_id":1029,"taxonomy_path":["Home & Living","Home D\u00e9cor","Wall D\u00e9cor","Wall Hangings"],"used_manufacturer":false,"is_vintage":false},{"listing_id":189332134,"state":"active","user_id":16798603,"category_id":null,"title":"Set of 4 Etched Aqua Wine Glasses with Live, Laugh, Love, Dream Theme","description":"Here is a set of 4 beautifully hand etched aqua wine glasses with Live, Laugh, Love, Dream Theme - This is a perfect glass set for any wine lover or kitchen that has wine decorations.   All glasses are done by hand with high speed air pressure and sand - they are in essence Hand-made and no two are alike. \n\nSee our blue wine glasses here - https:\/\/www.etsy.com\/listing\/124576143\/blue-12-ounce-wine-glasses-personalized.\n\nSee Our Green Glasses Here! https:\/\/www.etsy.com\/listing\/124577938\/green-wine-glasses-personalized-wedding","creation_tsz":1616730629,"ending_tsz":1627271429,"original_creation_tsz":1399911835,"last_modified_tsz":1616730629,"price":"29.99","currency_code":"USD","quantity":19,"sku":[],"tags":["wine glass","shower gift","wine glasses","etched wine glasses","birthday","Kitchen decor","Live","laugh","love","dream","painted wine glass","gift","blue"],"materials":["Glass"],"shop_section_id":28330427,"featured_rank":null,"state_tsz":1580298021,"url":"https:\/\/www.etsy.com\/listing\/189332134\/set-of-4-etched-aqua-wine-glasses-with?utm_source=thepuddinglistingima&utm_medium=api&utm_campaign=api","views":755,"num_favorers":21,"shipping_template_id":null,"processing_min":1,"processing_max":3,"who_made":"i_did","is_supply":"false","when_made":"made_to_order","item_weight":null,"item_weight_unit":"oz","item_length":null,"item_width":null,"item_height":null,"item_dimensions_unit":"in","is_private":false,"recipient":null,"occasion":null,"style":null,"non_taxable":false,"is_customizable":true,"is_digital":false,"file_data":"","should_auto_renew":true,"language":"en-US","has_variations":false,"taxonomy_id":1072,"taxonomy_path":["Home & Living","Kitchen & Dining","Drink & Barware","Barware","Wine Glasses & Charms"],"used_manufacturer":false,"is_vintage":false},{"listing_id":626480664,"state":"active","user_id":88141884,"category_id":null,"title":"Live Love Laugh Necklace, Heart Jewelry, Inspirational Gifts, Love Necklace, Sterling Silver","description":"Live Love Laugh Necklace ~ Live every moment! Live well, love much, laugh often! Three powerful life changing words.#lifegoals \n\nThis high quality sterling silver long pendant has a Live, Laugh, Love Print and is paired with a Sterling Silver Open Heart with Bronze Heart Charm. A gorgeous combination of both silver and bronze comes together to form this sweet design. The open heart is accented by a tiny warm bronze heart to add contrast and a layered look. Dangles on a sterling silver box chain and you can choose your length in the pull down menu. \n\nThe Live Laugh Love pendant measures 30.5mm in length and 12mm in width. \nThe Open Heart with Bronze Heart charm measures 18mm in length and 12 mm in width. See listing photo. \n\nComes with a polishing pad.  Wrapped with care and shipped in a gift box as listed ~ all ready for the giving!\n\nThank you so much for visiting Higher Grace Jewelry! We have a wide variety of jewelry, inspiring and thought-provoking, cherishing the simple beautiful moments of life and the loved ones who have been by our side forever. Explore all our collections at:\nhttps:\/\/www.etsy.com\/shop\/highergracejewelry\/\n\nLike us on Facebook and follow us on Instagram!\nhttps:\/\/www.facebook.com\/highergracejewelry\/\nhttps:\/\/www.instagram.com\/highergracejewelry\/\n\n{INTERNATIONAL ORDERS BE AWARE OF POSSIBLE ADDITIONAL FEES-}\nPlease be aware that your country may charge import duties, taxes and charges that are not included in the item price or shipping charges. The shipping charges are what my post office charges me to send the package to you. VAT charges and other import duties are the buyer&#39;s responsibility and vary by country. Please check with your country&#39;s customs office or the post office to determine what these additional costs will be prior to buying. These charges are normally collected by the delivering freight (shipping) company or when you pick up the item \u2013 do not confuse them for additional shipping charges.\n\nFeel free to message me with questions!\nBack to my shop: www.highergracejewelry.etsy.com","creation_tsz":1616728096,"ending_tsz":1627268896,"original_creation_tsz":1535613434,"last_modified_tsz":1616728096,"price":"63.50","currency_code":"USD","quantity":4,"sku":[],"tags":["live love laugh","necklace","heart jewelry","inspirational gifts","love necklace","sterling silver","love jewelry","live well","love much","laugh often","heart gifts","higher grace jewelry"],"materials":["Silver"],"shop_section_id":24396470,"featured_rank":null,"state_tsz":1607935561,"url":"https:\/\/www.etsy.com\/listing\/626480664\/live-love-laugh-necklace-heart-jewelry?utm_source=thepuddinglistingima&utm_medium=api&utm_campaign=api","views":147,"num_favorers":13,"shipping_template_id":50880591404,"processing_min":5,"processing_max":10,"who_made":"i_did","is_supply":"false","when_made":"made_to_order","item_weight":"4","item_weight_unit":"oz","item_length":"5","item_width":"5","item_height":"5","item_dimensions_unit":"in","is_private":false,"recipient":null,"occasion":null,"style":null,"non_taxable":false,"is_customizable":true,"is_digital":false,"file_data":"","should_auto_renew":true,"language":"en-US","has_variations":true,"taxonomy_id":1222,"taxonomy_path":["Jewelry","Necklaces","Charm Necklaces"],"used_manufacturer":false,"is_vintage":false},{"listing_id":493234445,"state":"active","user_id":64620235,"category_id":null,"title":"Wood Sign Naps Starbucks and Disney Sign 5&quot; X 7&quot; Lightweight Decorated for hanging Bar Kitchen Store Business Home Restaurant Wine Cellar","description":"This is a Wonderful Custom Personalized Sign.  Lightweight with holes for hanging and Cording added for easy hanging. (Indoor use)\n\nI love the saying of this sign,.  I had to make on for a good friend... as this sign really fit.  She works very hard long hours and needs to take naps, loves Starbucks and Disney.  This sign is perfect!\n\nI also have this sign in a painted version.  Here is the direct link:\nhttps:\/\/www.etsy.com\/listing\/498018527\/wood-color-sign-naps-starbucks-disney?ref=shop_home_feat_1\n\nGreat for a home, bar, store, wine ship, wine cellar, etc.  \n\nSize - 5  inches across by 7 inches tall.\nThere are 2 Holes with a string to hang the sign.  I can also make the sign without the holes.  Please let me know in the message area before checking out.  I will email and confirm the request.  \n\nMaterial - Veneer wood.  The best part of veneer wood is that it is light weight.  (For indoor use)\n\nPrice Includes the Custom Design Lettering\n\nIf there are any changes to the pattern that is shown, A proof will be sent to you for your approval before the order will be posted, so please check your Etsy email often.\n\nThank you for stopping by and please let me know if you have any questions.  I hope you will &quot;Like&quot; my store and share it with friends.\n\nTime frame depends when the item is purchased and how many orders I have before the purchase.  If you need this item by a certain date, please contact me before the purchase.  I will reply asap...\n\n\u2665:*\u00a8\u00a8*:\u2665:*\u00a8\u00a8*:\u2665:*\u00a8\u00a8*:\u2665:*\u00a8\u00a8*:\u2665:*\u00a8\u00a8*:\u2665:*\u00a8\u00a8*:\u2665:*\u00a8\u00a8*:\u2665:*\u00a8\u00a8*:\u2665\nPlease send me an e-mail with questions you may have about any of my items before your make your purchase. Most e-mails are answered within a few hours or up to 48 hours. Please take a look at the store policies prior to your purchase.\n\n\u2665:*\u00a8\u00a8*:\u2665:*\u00a8\u00a8*:\u2665:*\u00a8\u00a8*:\u2665:*\u00a8\u00a8*:\u2665:*\u00a8\u00a8*:\u2665:*\u00a8\u00a8*:\u2665:*\u00a8\u00a8*:\u2665:*\u00a8\u00a8*:\u2665\n\nPlease check store polices and info for additional information...\nhttps:\/\/www.etsy.com\/your\/shops\/LaserCreativeWorks?ref=seller_platform_hdr","creation_tsz":1616726813,"ending_tsz":1627267613,"original_creation_tsz":1479660585,"last_modified_tsz":1618933047,"price":"16.99","currency_code":"USD","quantity":3,"sku":[],"tags":["Wood Sign","Custom Veneer","Personalized Sign","Window Business","Wall Hanging","Home Decor","Door Hanger Design","Laser Creative Works","live laugh love","Disney sign Naps","Starbucks Sign Naps","Go TO Disney Sign","Go to Starbucks Sign"],"materials":["Laser","Veneer Wood","Design work","Pattern"],"shop_section_id":21035535,"featured_rank":null,"state_tsz":1618932974,"url":"https:\/\/www.etsy.com\/listing\/493234445\/wood-sign-naps-starbucks-and-disney-sign?utm_source=thepuddinglistingima&utm_medium=api&utm_campaign=api","views":360,"num_favorers":37,"shipping_template_id":null,"processing_min":null,"processing_max":null,"who_made":"i_did","is_supply":"false","when_made":"made_to_order","item_weight":null,"item_weight_unit":"oz","item_length":null,"item_width":null,"item_height":null,"item_dimensions_unit":"in","is_private":false,"recipient":null,"occasion":null,"style":null,"non_taxable":false,"is_customizable":true,"is_digital":false,"file_data":"","should_auto_renew":false,"language":"en-US","has_variations":true,"taxonomy_id":1100,"taxonomy_path":["Home & Living","Office","Message & Bulletin Boards"],"used_manufacturer":false,"is_vintage":false},{"listing_id":974461816,"state":"active","user_id":461016302,"category_id":null,"title":"Family \/ Home Bundle - 12 Pk SVG, PNG, EPS","description":"Cute Family and Home Bundle. 12 Pk. Great for use with Cricut. Designs for home crafting. SVG, EPS, PNG.","creation_tsz":1616726719,"ending_tsz":1627267519,"original_creation_tsz":1616726719,"last_modified_tsz":1616816495,"price":"3.00","currency_code":"USD","quantity":100,"sku":[],"tags":["Home","Family","Decor","SVG","Cricut","Craft","Digital","Love","EPS","PNG","Laugh","Live","Fun"],"materials":[],"shop_section_id":33275427,"featured_rank":null,"state_tsz":1616726720,"url":"https:\/\/www.etsy.com\/listing\/974461816\/family-home-bundle-12-pk-svg-png-eps?utm_source=thepuddinglistingima&utm_medium=api&utm_campaign=api","views":3,"num_favorers":0,"shipping_template_id":null,"processing_min":null,"processing_max":null,"who_made":"i_did","is_supply":"false","when_made":"2020_2021","item_weight":null,"item_weight_unit":"oz","item_length":null,"item_width":null,"item_height":null,"item_dimensions_unit":"in","is_private":false,"recipient":null,"occasion":null,"style":null,"non_taxable":false,"is_customizable":false,"is_digital":true,"file_data":"3 ZIP","should_auto_renew":true,"language":"en-US","has_variations":false,"taxonomy_id":77,"taxonomy_path":["Art & Collectibles","Drawing & Illustration","Digital"],"used_manufacturer":false,"is_vintage":false},{"listing_id":670529779,"state":"active","user_id":193329451,"category_id":null,"title":"Laughback Definition- Unisex Short Sleeve Tee- Funny Hipster Good Memories Shirt For Nostalgic Lover Happiness Minimalist positive vibes","description":"*** ALL SALES ARE FINAL ***\n\nReplanting our world, 1 tee at a time.\n\n\nPrint Provider Update:\n\nIn an effort to improve design positioning on our t-shirt garments, our print provider has decided to position the front print area 1.5 inches lower than what is shown on our listings. This change will come into effect for orders placed on March 25th and after.\n\nWe will be working to adjust all of our listing photos to more accurately represent this change, which may take a few weeks. In the meantime, please be aware that the designs on your purchased t-shirt will appear 1.5 inches lower than indicated in our photos on March 25th and after until all listing photos have been updated. Thanks!\n\n\n\nWith our unique and fun designs, your new shirt will look and feel awesome. Pun and Pine&#39;s unisex adult tees are made from 100% combed ring spun cotton that results in a smoother and longer lasting fabric.\n\n\nHere are the deets of your soon to be new shirt:\n\n- 100% combed and ring spun cotton. ( Heather colors contain Polyester)\n\n- Printed with eco-friendly inks.\n\n- Printed and shipped from the U.S.\n\n- Shoulder taped with side seams for the best fit.\n\n- Ribbed knit collar with seams.\n\n- This purchase plants 1 tree (see About section)\n\n\nSizing deets: Please refer to sizing chart in each shirt thumbnail for measurements.\n\nPlease note: Due to the nature of the manufacturing process, slight variations in\nt-shirt color may occur.Thank you!","creation_tsz":1616724661,"ending_tsz":1627265461,"original_creation_tsz":1545964355,"last_modified_tsz":1616724661,"price":"23.00","currency_code":"USD","quantity":998,"sku":["441868581","441868692","441868809","441868926","441869160","441868701","441868818","441869169","441868728","441868845","441868962","441869079","441869196","441869223","441869340","441869043","441869277","441868590","441868935","441869052","441869286","441868602","441869313","441868647","441868755","441868872","441868989","441869106"],"tags":["laughback tee","happiness shirt","good memories","hipster friend's top","gift for him","gift for her","valentine's day gift","live laugh love","tee addict","positive vibes shirt","nostalgic lover","minimalist gift","funny definition"],"materials":[],"shop_section_id":null,"featured_rank":null,"state_tsz":1545964355,"url":"https:\/\/www.etsy.com\/listing\/670529779\/laughback-definition-unisex-short-sleeve?utm_source=thepuddinglistingima&utm_medium=api&utm_campaign=api","views":40,"num_favorers":5,"shipping_template_id":67907940065,"processing_min":1,"processing_max":7,"who_made":"someone_else","is_supply":"false","when_made":"made_to_order","item_weight":null,"item_weight_unit":"g","item_length":null,"item_width":null,"item_height":null,"item_dimensions_unit":"mm","is_private":false,"recipient":null,"occasion":null,"style":null,"non_taxable":false,"is_customizable":false,"is_digital":false,"file_data":"","should_auto_renew":true,"language":"en-US","has_variations":true,"taxonomy_id":482,"taxonomy_path":["Clothing","Unisex Adult Clothing","Tops & Tees","T-shirts"],"used_manufacturer":false,"is_vintage":false},{"listing_id":910135653,"state":"active","user_id":55757584,"category_id":null,"title":"Live Laugh Love Wall Art | Motivational Canvas | Large Art Decor |  Abstract Art | Modern Art Decor | Abstract Watercolor  | Canvas Wall Art","description":"CANVAS DETAILS:\n\n\u2022 This is a Museum Quality Canvas Print, not a plain paper or a poster.\n\u2022 All canvases are produced by hand from start to finish in our Studio.\n\u2022 Premium Canvas is wrapped on the solid wood frame.\n\u2022 This canvas gallery wrap has vibrant and rich colors!\n\u2022 Canvas has a 0.75 or 1.5 depth(depend on what you select).\n\u2022 Pigment based inks for exception fade resistance.\n\u2022 Printed on premium quality cotton canvas material.\n\u2022 Our canvas prints are guaranteed to look fabulous for years to come.\n\u2022 Please note due to computer monitors differences in colors may vary.\n\u2022 Your satisfaction is 100% guaranteed- please contact us about any problems.\n\n100% MADE IN USA.\n\n\nPLEASE NOTE: Printing and shipping times are estimates and not guaranteed. We unfortunately can&#39;t control what happens once a product is shipped, and delays and lost packages due to shipping company errors can occur. If your order is taking longer than it should to arrive, please contact us right away so we can look into for you.","creation_tsz":1616723448,"ending_tsz":1627264248,"original_creation_tsz":1606118573,"last_modified_tsz":1616741049,"price":"47.00","currency_code":"USD","quantity":999,"sku":["Art 136 | 1"],"tags":["Abstract Painting","Canvas Abstract Art","Abstract Wall Art","Modern Wall Art","Abstract Canvas Art","Large Abstract Art","Contemporary Art","Abstract Art","Canvas Wall Art","Minimalist Art","Strong Mindset Art","Motivational Art","Live Laugh Love Art"],"materials":["INK","CANVAS","WOOD FRAME","STAPLES"],"shop_section_id":31170571,"featured_rank":null,"state_tsz":1606118573,"url":"https:\/\/www.etsy.com\/listing\/910135653\/live-laugh-love-wall-art-motivational?utm_source=thepuddinglistingima&utm_medium=api&utm_campaign=api","views":8,"num_favorers":0,"shipping_template_id":null,"processing_min":1,"processing_max":3,"who_made":"i_did","is_supply":"false","when_made":"made_to_order","item_weight":"17","item_weight_unit":"oz","item_length":"1","item_width":"1","item_height":"1","item_dimensions_unit":"in","is_private":false,"recipient":null,"occasion":null,"style":null,"non_taxable":false,"is_customizable":false,"is_digital":false,"file_data":"","should_auto_renew":true,"language":"en-US","has_variations":true,"taxonomy_id":1028,"taxonomy_path":["Home & Living","Home D\u00e9cor","Wall D\u00e9cor","Wall Decals & Murals"],"used_manufacturer":false,"is_vintage":false},{"listing_id":810572793,"state":"active","user_id":306797147,"category_id":null,"title":"LIVE LOVE LAUGH vinyl record clock","description":"Searching for a gift for that special person that&#39;s difficult to shop for? Well I&#39;ve got the perfect present! Snatch up this modern 12&quot;x12&quot;  Vinyl record clock, which runs on a silent analog function, so you don&#39;t have to worry about that consistent ticking sound.Perfect for living rooms, office spaces, and bedrooms! Makes an amazing gift! and conversation piece! Each clock is truly unique and made of a different recycled record, promoting a more eco-friendly environment.Clock uses 1 AA battery (Not included.)Ships by USPS priority mail, with tracking numbers, it ships to your door in less than a week! Products are well-packaged and come with a 100% satisfaction guarantee.\nMADE IN THE USA - BALTIMORE MARYLAND","creation_tsz":1616722241,"ending_tsz":1627263041,"original_creation_tsz":1589720336,"last_modified_tsz":1616722241,"price":"39.99","currency_code":"USD","quantity":99,"sku":[],"tags":["vinyl record clock","clock","record clocks","CLOCKS","mancave","GAME ROOM","LIVE LOVE LAUGH","HOME DECOR CLOCKS","LIVING ROOM CLOCKS","LIVING ROOM CLOCK","MODERN CLOCKS","MODERN CLOCK","BIRTHDAY GIFTS"],"materials":[],"shop_section_id":29190900,"featured_rank":null,"state_tsz":1608843780,"url":"https:\/\/www.etsy.com\/listing\/810572793\/live-love-laugh-vinyl-record-clock?utm_source=thepuddinglistingima&utm_medium=api&utm_campaign=api","views":38,"num_favorers":3,"shipping_template_id":92899439739,"processing_min":1,"processing_max":3,"who_made":"i_did","is_supply":"false","when_made":"2020_2021","item_weight":"16","item_weight_unit":"oz","item_length":"13","item_width":"13","item_height":"3","item_dimensions_unit":"in","is_private":false,"recipient":null,"occasion":null,"style":null,"non_taxable":false,"is_customizable":false,"is_digital":false,"file_data":"","should_auto_renew":true,"language":"en-US","has_variations":false,"taxonomy_id":1016,"taxonomy_path":["Home & Living","Home D\u00e9cor","Clocks"],"used_manufacturer":false,"is_vintage":false},{"listing_id":560812342,"state":"active","user_id":47170132,"category_id":null,"title":"Live Laugh Love, Korean print, Home decor gifts, Home decor printables, Special day gift, PRINTABLE for home","description":"Live Laugh Love, Korean print, Home decor gifts, Home decor printables, Special day gift, PRINTABLE for home\n\nThis listing is for a DIGITAL FILE of this artwork.\n\nHangul (the Korean written language) is a beautiful way to display simple words for you or guests of your home to enjoy. This is the first piece of the Love series. \n\nYou&#39;re purchasing a DIGITAL FILE, which can be printed at any print shop or even print on your own printer at home.  Save money by purchasing this digital file and printing yourself.  \n\nYou will receive 5 high resolution (300 DPI files):\nJPG - 5x7\nJPG - 8x10\nJPG - 11x14\nJPG - 16x20\nJPG - 18x24 \n\nNEED A DIFFERENT SIZE?  Please let me know in the &#39;note to seller&#39; at the checkout, I will resize the file and send it to your email address.\n\nDON\u2019T SEE THE BIBLE VERSE\/QUOTE\/WORD YOU LIKE? \nIf you have any ideas or specific quotes that you\u2019d like to see in my shop, please send me a convo and let me know!\n\nSHIPPING:\nTHIS IS A DIGITAL PRINT - NO PHYSICAL PRODUCT WILL BE SHIPPED.  You&#39;ll be able to download and print this art instantly, as soon as you purchase.  Simply go to http:\/\/www.etsy.com\/your\/purchases to find your downloads after purchasing.\n\nHOW TO PRINT:\nPrint at home or any professional printing company.  We suggest spending few extra cents and use a nice heavyweight matte paper.  Some printers such as Staples also have great options to print on canvas for a good price.  \n\nFOLLOW ME \nInstagram | Pinterest | Facebook - @KoreanScribbles\n\nLicense is for PERSONAL USE ONLY. You can print this artwork for yourself or use the print as a gift, but you cannot share or resell the digital files or printed artwork.  \n\nGiven the nature of this product, there are NO RETURNS.  But, if you have trouble downloading or printing, please contact me and I&#39;m VERY happy to help!!","creation_tsz":1616721644,"ending_tsz":1627262444,"original_creation_tsz":1511517573,"last_modified_tsz":1616721644,"price":"4.45","currency_code":"USD","quantity":47,"sku":[],"tags":["live laugh love","home decor gifts","home decor","printables","special day gift","printable for home","Korean print"],"materials":[],"shop_section_id":22843129,"featured_rank":null,"state_tsz":1518421268,"url":"https:\/\/www.etsy.com\/listing\/560812342\/live-laugh-love-korean-print-home-decor?utm_source=thepuddinglistingima&utm_medium=api&utm_campaign=api","views":120,"num_favorers":11,"shipping_template_id":null,"processing_min":null,"processing_max":null,"who_made":"i_did","is_supply":"false","when_made":"2010_2019","item_weight":null,"item_weight_unit":"oz","item_length":null,"item_width":null,"item_height":null,"item_dimensions_unit":"in","is_private":false,"recipient":null,"occasion":null,"style":null,"non_taxable":false,"is_customizable":false,"is_digital":true,"file_data":"5 JPG","should_auto_renew":true,"language":"en-US","has_variations":false,"taxonomy_id":2078,"taxonomy_path":["Art & Collectibles","Prints","Digital Prints"],"used_manufacturer":false,"is_vintage":false},{"listing_id":988374129,"state":"active","user_id":5656388,"category_id":null,"title":"Live, Love, Laugh, Pink Ribbon  Resin Cast Handmade Sierra Acrylic  Twist Ballpoint Pen Parker  Chrome, Black Trim","description":"This is a Handmade Sierra Twist Pen made With My Own  Cast In Graphics Acrylic Blank \n\nLIVE, LOVE, LAUGH, PINK RIBBON GRAPHICS. \n\nI have been making these unique and elegant writing instruments in my home shop for some time. \n\nIt comes with CHROME, BLACK Plated Trim , and Twist Action Operation. \n\nPen writes in Black Ink and uses Parker Style Ballpoint Refills which can be found in any office supply store. \nCAN ALSO USE A PARKER STYLE GEL WRITER TYPE REFILL.\n\nIt fits comfortably in your hand and is a pleasure to write with. \n\nEach pen is shipped in a White Cotton Filled  Box.\n\nI have other items listed for sale so please check those as well. \n\nContact me with any questions or special requests.","creation_tsz":1616720990,"ending_tsz":1627261790,"original_creation_tsz":1616720990,"last_modified_tsz":1616724330,"price":"25.99","currency_code":"USD","quantity":1,"sku":[],"tags":["pen","pens","lathe turned","parker","twist pen","ballpoint pen","handmade pink pen","pink ribbon pen","handmade sierra pink","chrome black trim","LIVE LOVE LAUGH PEN"],"materials":["chrome","ballpoint","parker refill","sierra","pink acrylic","pink ribbon"],"shop_section_id":11678427,"featured_rank":null,"state_tsz":1616720990,"url":"https:\/\/www.etsy.com\/listing\/988374129\/live-love-laugh-pink-ribbon-resin-cast?utm_source=thepuddinglistingima&utm_medium=api&utm_campaign=api","views":2,"num_favorers":0,"shipping_template_id":8684254,"processing_min":1,"processing_max":2,"who_made":"i_did","is_supply":"false","when_made":"2010_2019","item_weight":null,"item_weight_unit":"oz","item_length":null,"item_width":null,"item_height":null,"item_dimensions_unit":"in","is_private":false,"recipient":null,"occasion":null,"style":null,"non_taxable":false,"is_customizable":true,"is_digital":false,"file_data":"","should_auto_renew":false,"language":"en-US","has_variations":false,"taxonomy_id":1,"taxonomy_path":["Accessories"],"used_manufacturer":false,"is_vintage":false},{"listing_id":642117095,"state":"active","user_id":44231466,"category_id":null,"title":"Be our Guest | 16x16 Pillow & Insert | Home Decor | Meditation | Throw Pillow | Graduation Gift | Primitive Decor | Gift for Her","description":"Part of a limited selection of seasonal throw pillows we stock to accent our pillow line.\n\nAren&#39;t guest rooms difficult to decorate? You want the decor to be inviting and stylish, but nothing that needs be changed too often, and you generally want a neutral color palette so anyone of any age or gender can appreciate it. But one thing is for sure, every guest wants to feel welcome and at home. Place this soft and inviting complementary pillow on your guest room bed to get a five star hostess rating!\n\nMade from a lovely cotton polyester blend material and is pre-filled, ready to use.  This is a complete pillow with stuffing.\n\nSize: 16&quot;x16&quot; square\n\n* Please note, this order is for 1 pillow.  The image is to show the back pattern of the pillow you are ordering.","creation_tsz":1616719853,"ending_tsz":1627260653,"original_creation_tsz":1536291343,"last_modified_tsz":1616948468,"price":"29.95","currency_code":"USD","quantity":2,"sku":["PKBeOurGuest"],"tags":["love quotes","i love you gifts","love decor","love live","live laugh love","valentine decor","valentines gift","valentines day decor","love throw pillows","throw pillow sets","Inspirational Quotes","Positive Quotes","strength quotes"],"materials":["Cotton","Polyester"],"shop_section_id":24653478,"featured_rank":null,"state_tsz":1611450154,"url":"https:\/\/www.etsy.com\/listing\/642117095\/be-our-guest-16x16-pillow-insert-home?utm_source=thepuddinglistingima&utm_medium=api&utm_campaign=api","views":21,"num_favorers":2,"shipping_template_id":44292890477,"processing_min":1,"processing_max":2,"who_made":"collective","is_supply":"false","when_made":"2020_2021","item_weight":"8","item_weight_unit":"oz","item_length":"16","item_width":"16","item_height":"2","item_dimensions_unit":"in","is_private":false,"recipient":null,"occasion":null,"style":null,"non_taxable":false,"is_customizable":false,"is_digital":false,"file_data":"","should_auto_renew":true,"language":"en-US","has_variations":false,"taxonomy_id":1017,"taxonomy_path":["Home & Living","Home D\u00e9cor","Decorative Pillows"],"used_manufacturer":false,"is_vintage":false},{"listing_id":526998755,"state":"active","user_id":44231466,"category_id":null,"title":"Dream Catcher | Pillow Cover | Throw Pillow | Boho Pillow | Home Decor | Spirit of Fairy | Famous Quotes | Motivational Quotes | Room Decor","description":"100% Hand Made.  Made in America.\n\nMost of us made a basic one of these in kindergarten, right? If this design doesn&#39;t hit the boho bullseye, we don&#39;t know what will! We all know someone who seems to fit this quote: &quot;She has the Soul of a Gypsy The Heart of a Hippie The Spirit of a Fairy.&quot;  So why not gift it to them for a birthday, anniversary, off-to-college gift, or for Christmas?\n\nDETAILS:\n1 Accent Pillow Cover\nSize: Approx 10x10,12x12,14x14,16x16,18x18,20x20\nCover Front:  Dream Catcher - She has the Soul of a Gypsy on White Background\nCover Back: Stark White\nClosure: Concealed Zipper\nFabric: Cotton \/ Polyester Blend - Neatly woven, sturdy material\nOther: Re-enforced zipper opening ends.\nEdges over-sewn\nQuality checked, inside and out.\n\nCARE SUGGESTIONS:\n- Spot Clean or Hand Wash, do not bleach. Lay flat or hang to dry.\n- Touch up with warm, not hot iron, preferably over a slightly damp press cloth, if needed.","creation_tsz":1616719593,"ending_tsz":1627260393,"original_creation_tsz":1493138011,"last_modified_tsz":1617827531,"price":"22.00","currency_code":"USD","quantity":1000,"sku":["dreamcatcherwhite"],"tags":["love quotes","i love you gifts","love decor","love live","live laugh love","valentine decor","valentines gift","valentines day decor","love throw pillows","throw pillow sets","Inspirational Quotes","Positive Quotes","strength quotes"],"materials":["Cotton"],"shop_section_id":19911735,"featured_rank":null,"state_tsz":1614134409,"url":"https:\/\/www.etsy.com\/listing\/526998755\/dream-catcher-pillow-cover-throw-pillow?utm_source=thepuddinglistingima&utm_medium=api&utm_campaign=api","views":1353,"num_favorers":204,"shipping_template_id":44292890477,"processing_min":1,"processing_max":2,"who_made":"i_did","is_supply":"false","when_made":"2020_2021","item_weight":"5","item_weight_unit":"oz","item_length":"9","item_width":"9","item_height":"1","item_dimensions_unit":"in","is_private":false,"recipient":null,"occasion":null,"style":null,"non_taxable":false,"is_customizable":true,"is_digital":false,"file_data":"","should_auto_renew":true,"language":"en-US","has_variations":true,"taxonomy_id":1017,"taxonomy_path":["Home & Living","Home D\u00e9cor","Decorative Pillows"],"used_manufacturer":false,"is_vintage":false},{"listing_id":159738252,"state":"active","user_id":10083339,"category_id":null,"title":"Inspirational Driftwood Art Hanging Sign: Live Simply, Dream Big, Be Grateful, Give Love, Laugh Lots, Painting, Driftwood Art","description":"Made with beachy crystals, driftwood, and colorful beads, this one of a kind sign will surely inspire you to start the new year right!\n\nLive Simply in green\nDream Big in purple\nBe Grateful in blue\nGive Love in red\nLaugh Lots in yellow\n\nMeasurements: hangs 18&quot; total, 11&quot; across","creation_tsz":1616719242,"ending_tsz":1627260042,"original_creation_tsz":1376592659,"last_modified_tsz":1616719242,"price":"50.00","currency_code":"USD","quantity":8,"sku":[],"tags":["driftwood","reclaimed wood","driftwood art","live simply","dream big","give love","laugh lots","inspirational quotes","inspirational sign","coastal decor","beach home decor","valentines day decor","valentines day gift"],"materials":["driftwood","wood","reclaimed wood","beads","stone beads","crystal beads","colorful","bright colors","green","purple","blue","red","yellow"],"shop_section_id":11630865,"featured_rank":null,"state_tsz":1607700013,"url":"https:\/\/www.etsy.com\/listing\/159738252\/inspirational-driftwood-art-hanging-sign?utm_source=thepuddinglistingima&utm_medium=api&utm_campaign=api","views":3168,"num_favorers":148,"shipping_template_id":124907849,"processing_min":3,"processing_max":5,"who_made":"i_did","is_supply":"false","when_made":"made_to_order","item_weight":null,"item_weight_unit":"oz","item_length":null,"item_width":null,"item_height":null,"item_dimensions_unit":"in","is_private":false,"recipient":null,"occasion":null,"style":["Beach","Hippie"],"non_taxable":false,"is_customizable":true,"is_digital":false,"file_data":"","should_auto_renew":true,"language":"en-US","has_variations":false,"taxonomy_id":2844,"taxonomy_path":["Home & Living","Home D\u00e9cor","Wall D\u00e9cor","Wall Hangings","Signs"],"used_manufacturer":false,"is_vintage":false},{"listing_id":213275756,"state":"active","user_id":44475156,"category_id":null,"title":"Love with Jesus Fish - Car\/Truck\/Phone\/Computer\/Home\/Laptop Decal","description":"Note: All decals are di-cut. The decals Do Not include a wood\/fencing background. \n\nWelcome to Decal Phanatics!\r\n\r\nCUSTOM SIZES AND DESIGNS ARE AVAILABLE\r\n-Brand New Decals\r\n-5 Year Vinyl\r\n-Waterproof, Durable\r\n-Includes Transfer Tape applied to decal for smooth installation\r\n\r\nPayment Terms:\r\nPaypal, Credit Cards, and Debit Cards \r\nShipping within the US is $1.99 plus $0.25 for each additional decal\r\n\r\nReturn Policy:\r\nAccepted for unused items only.  \r\n\r\n100% Satisfaction Guarantee\r\n\r\nInstallation: \r\n1. Clean application area. Use water (no Windex). Do not apply on extremely hot or cold surfaces.  \r\n2. Prepare the decal by rubbing a credit card across the clear transfer tape\r\n3. Peel the white paper backing off the sticker\r\n4. Slowly place the decal onto the desired surface. Rub\/Press decal firmly with credit card. \r\n5. Slowly peel the clear transfer tape off at from the top corner. Do not pull decal off while peeling transfer tape. \r\n\r\nAreas of Application: Car\/Truck Windows, Car Body Surfaces, Bikes, Helmets, Motorcycles, Computers, Skateboards, Snowboards, Guitars, Mirrors, Laptops, Home Walls, Home Windows, Store Windows, Doors, Laminate, Boats, Toolboxes, etc. \r\n\r\nContact me at decalphanatics@gmail.com for any questions, concerns, custom orders.\r\n\r\nThanks!","creation_tsz":1616719233,"ending_tsz":1627260033,"original_creation_tsz":1417294563,"last_modified_tsz":1616719233,"price":"1.99","currency_code":"USD","quantity":28,"sku":[],"tags":["car decal","computer decal","laptop decal","bumper sticker","macbook decal","phone decal","love","love decal wall art","jesus fish","jesus","christian","jesus bumper sticker","love live laugh"],"materials":["vinyl decal"],"shop_section_id":15148502,"featured_rank":null,"state_tsz":1573389624,"url":"https:\/\/www.etsy.com\/listing\/213275756\/love-with-jesus-fish?utm_source=thepuddinglistingima&utm_medium=api&utm_campaign=api","views":195,"num_favorers":45,"shipping_template_id":2313951287,"processing_min":1,"processing_max":3,"who_made":"i_did","is_supply":"false","when_made":"made_to_order","item_weight":null,"item_weight_unit":"oz","item_length":null,"item_width":null,"item_height":null,"item_dimensions_unit":"in","is_private":false,"recipient":null,"occasion":null,"style":null,"non_taxable":false,"is_customizable":true,"is_digital":false,"file_data":"","should_auto_renew":true,"language":"en-US","has_variations":true,"taxonomy_id":1319,"taxonomy_path":["Paper & Party Supplies","Paper","Stickers, Labels & Tags","Bumper Stickers"],"used_manufacturer":false,"is_vintage":false},{"listing_id":562126923,"state":"active","user_id":36088109,"category_id":null,"title":"1 Heart Charm Silver Stainless Steel Live Laugh Love (1-1325)","description":"Quantity: You will receive 1 heart pendant.\n\nColor: Silver\n\nMeasurements: 21mm X 17mm; Includes a 5mm jumpring.\n\nMaterial: 316 Stainless Steel\n\n\nPlease remember that the color reflected in the images may be slightly different than the actual color due to differences in monitor screen settings and resolution.","creation_tsz":1616714417,"ending_tsz":1627255217,"original_creation_tsz":1506994738,"last_modified_tsz":1616714417,"price":"3.25","currency_code":"USD","quantity":11,"sku":[],"tags":["heart charms","heart pendant","silver heart pendant","silver heart charms","silver hearts","heart charm","stainless steel","jewelartology","hearts","heart","316 stainless steel","love charms","live laugh love"],"materials":["Steel"],"shop_section_id":22322007,"featured_rank":null,"state_tsz":1506994741,"url":"https:\/\/www.etsy.com\/listing\/562126923\/1-heart-charm-silver-stainless-steel?utm_source=thepuddinglistingima&utm_medium=api&utm_campaign=api","views":131,"num_favorers":24,"shipping_template_id":5415754035,"processing_min":1,"processing_max":3,"who_made":"someone_else","is_supply":"true","when_made":"2010_2019","item_weight":null,"item_weight_unit":"oz","item_length":null,"item_width":null,"item_height":null,"item_dimensions_unit":"in","is_private":false,"recipient":null,"occasion":null,"style":null,"non_taxable":false,"is_customizable":false,"is_digital":false,"file_data":"","should_auto_renew":true,"language":"en-US","has_variations":false,"taxonomy_id":6427,"taxonomy_path":["Craft Supplies & Tools","Beads, Gems & Cabochons","Charms & Pendants","Pendants"],"used_manufacturer":false,"is_vintage":false},{"listing_id":719906545,"state":"active","user_id":53235611,"category_id":null,"title":"Live Laugh Love Wooden Wall Words","description":"Live Laugh Love Words Laser Cut Wood and painted your selected color. The 30&quot; over all width, Live measures 8&quot; x 5 1\/2&quot;, Love measures 8&quot; x 5 1\/2&quot; and Laugh measures 12&quot; x 7 1\/2&quot; and all are 1\/4&quot; thick\nThe 40&quot; over all width, Live measures 10&quot; x 7 1\/4&quot;, Love measures 10&quot; x 7 1\/4&quot; and Laugh measures 16&quot; x 10&quot; and all are 1\/4&quot; thick","creation_tsz":1616712000,"ending_tsz":1627252800,"original_creation_tsz":1562624606,"last_modified_tsz":1616712000,"price":"19.95","currency_code":"USD","quantity":24,"sku":[],"tags":["Live","Laugh","Love","Wall Sign","Motorhead","Art","Wall Art","Garage Art","Laser Etched","Wooden","Engraved","Wall Decor","Black"],"materials":["Wood","Paint"],"shop_section_id":18236883,"featured_rank":null,"state_tsz":1616712000,"url":"https:\/\/www.etsy.com\/listing\/719906545\/live-laugh-love-wooden-wall-words?utm_source=thepuddinglistingima&utm_medium=api&utm_campaign=api","views":507,"num_favorers":44,"shipping_template_id":null,"processing_min":1,"processing_max":3,"who_made":"i_did","is_supply":"false","when_made":"made_to_order","item_weight":null,"item_weight_unit":"oz","item_length":null,"item_width":null,"item_height":null,"item_dimensions_unit":"in","is_private":false,"recipient":null,"occasion":null,"style":["Art Deco","Abstract"],"non_taxable":false,"is_customizable":true,"is_digital":false,"file_data":"","should_auto_renew":true,"language":"en-US","has_variations":true,"taxonomy_id":1002,"taxonomy_path":["Home & Living","Home D\u00e9cor"],"used_manufacturer":false,"is_vintage":false},{"listing_id":898193449,"state":"active","user_id":313135986,"category_id":null,"title":"Live Love Laugh Letter Resin Mold, 3 in 1 Letter Mold, Lifestyle Resin Mold, Alphabet Letter Mold, DIY Home Decoration Wall Decoration","description":"Item Description:\n\nMaterial:Silicone\nSize: As pic shows\nQuantity: 1 pcs of silicone mold\n\nFeatures:\n\n100% brand new and high quality\nWide range temperature tolerance: -40 centigrade to+210 centigrade\n\n\nNote:\nDue to manual measurement, the size may have 1-3mm error\nDue to variations in monitor display, the color of products may slightly be different when received in person","creation_tsz":1616710998,"ending_tsz":1627251798,"original_creation_tsz":1604478929,"last_modified_tsz":1616710998,"price":"9.20","currency_code":"USD","quantity":14,"sku":["mszfmo402"],"tags":["resin molds","silicone mold","resin mold silicone","DIY Jewelry Making","Jewelry Making Tools","resin decorations","letter sign mold","resin letter mold","Resin Decoration","DIY Home Decoration","DIY wall decoration","live love laugh","love letter mold"],"materials":["Silicone"],"shop_section_id":29262270,"featured_rank":null,"state_tsz":1612836928,"url":"https:\/\/www.etsy.com\/listing\/898193449\/live-love-laugh-letter-resin-mold-3-in-1?utm_source=thepuddinglistingima&utm_medium=api&utm_campaign=api","views":85,"num_favorers":53,"shipping_template_id":96187689792,"processing_min":3,"processing_max":7,"who_made":"someone_else","is_supply":"true","when_made":"2020_2021","item_weight":null,"item_weight_unit":"g","item_length":null,"item_width":null,"item_height":null,"item_dimensions_unit":"mm","is_private":false,"recipient":null,"occasion":null,"style":null,"non_taxable":false,"is_customizable":false,"is_digital":false,"file_data":"","should_auto_renew":true,"language":"en-US","has_variations":false,"taxonomy_id":6227,"taxonomy_path":["Craft Supplies & Tools","Molds"],"used_manufacturer":false,"is_vintage":false},{"listing_id":642188241,"state":"active","user_id":40921599,"category_id":null,"title":"Live More Laugh More Love More Gilmore Girls Tee | Women&#39;s Graphic Tee | Gilmore Girls T-Shirt | Gilmore Girls Shirt | Lorelai and Rory Tee","description":"Are you a Gilmore Girls fan?  Then this fun graphic tee is sure to please!  \n\nThis updated UNISEX essential tee is AMAZING!  It\u2019s not just another boyfriend tee. This tee fits like a well-loved favorite with its crew neck, short sleeves and Airlume combed and ring-spun cotton.  SO SOFT and comfy!  It\u2019s perfect for layering and can be dressed up for a night out or down for a comfortable casual look. \n\n\u2192 UNISEX Sizes Available:\nSmall, Medium, Large, X-Large, and XX-Large\n\nIMPORTANT NOTE:\n\nThis is a UNISEX tee.  Most women order their normal size for a looser fit or size down for a more fitted look.\n\n{{ Please view the sizing chart located in the above images before ordering.}}\n\n------HOW TO ORDER------\n\n1.  Simply choose your SHIRT SIZE and COLOR from the drop down menus on the top right.\n\n2.  During check out, leave a note in the \u201cnotes to seller&quot; section with your choice of vinyl color for the font\/graphics.  Font color options are pictured in the images above.  We have many in stock font color options to choose from.  If you have a little more time and want to show your creativity, we offer even more special order vinyl color options for no additional charge.\n\n* We have a lot of special order vinyl colors already in stock, but in limited quantities.  If you would like a special order vinyl color, it usually only adds 1-3 extra processing days to your order.  Please don\u2019t hesitate to ask if you have questions.\n\n\n------SHIPPING------\n\nAll orders are shipped within 3-5 BUSINESS days via USPS and tracking information will be uploaded as soon as it&#39;s shipped for your convenience.  Please keep in mind if your ship by date falls on a US holiday, your order will ship the next business day.\n\n\u2192 If you need a rush order, please contact us prior to ordering to ensure we can accommodate you.  Additional costs may apply.\n\n\u2192 Please feel free to contact us with any questions or special requests. Custom ordering is always welcome.\n\n\u2192 Please be sure to read our Shipping & Policies page and our FAQs before purchasing for more detailed information on production and shipping times, as well as our return\/exchange policy.\n\nBe Kind Designs Co. strives for 100% customer satisfaction. Please, do not hesitate to contact us with any concern.  We are here to help.\n\nIn order to provide an exceptional quality product, our garments all come from Bella + Canvas and are made with high quality Siser heat transfer vinyl or glitter and are hand pressed using a professional heat press in our home studio with special care to detail.  \n\n------CARE INSTRUCTIONS------\n\nWash garment inside out on gentle or delicate cycle in cold water.  Dry garment inside out on low setting.  Do not bleach.  Do not iron directly on design.  If ironing is needed, turn garment inside out and iron.\n\nGarment Specifications:\n\nUnisex Tee Description: \n\u2192Side-seamed\n\u2192Shoulder taping\n\u2192Fitted at bicep\n\u2192Retail fit\n\u2192Unisex sizing\n\nSolid Colors: \n\u2192100% Airlume combed and ring-spun cotton\n\u219232 singles\n\u21924.2 oz.\nBlack Heather:\n\u219290% Airlume combed and ring-spun cotton\n\u219210% polyester\nHeather CVC\/Blend Colors:\n\u219252% Airlume combed and ring-spun cotton\n\u219248% polyester","creation_tsz":1616710851,"ending_tsz":1627251651,"original_creation_tsz":1536328646,"last_modified_tsz":1616710851,"price":"20.00","currency_code":"USD","quantity":19,"sku":[],"tags":["Clothing","Women's Clothing","Tops and Tees","T-shirts","Unisex t shirt","Be Kind Designs Co","Plus Size Shirt","Women's Graphic Tees","Gilmore Girls","Gilmore Girls Shirts","Lorelai Rory Gilmore","Live More Love More","Laugh More Gilmore"],"materials":["Bella Canvas","Siser Heat Transfer Vinyl"],"shop_section_id":20370399,"featured_rank":null,"state_tsz":1596463591,"url":"https:\/\/www.etsy.com\/listing\/642188241\/live-more-laugh-more-love-more-gilmore?utm_source=thepuddinglistingima&utm_medium=api&utm_campaign=api","views":254,"num_favorers":42,"shipping_template_id":61416680365,"processing_min":3,"processing_max":5,"who_made":"i_did","is_supply":"false","when_made":"made_to_order","item_weight":"9","item_weight_unit":"oz","item_length":"13","item_width":"10","item_height":"2","item_dimensions_unit":"in","is_private":false,"recipient":null,"occasion":null,"style":null,"non_taxable":false,"is_customizable":true,"is_digital":false,"file_data":"","should_auto_renew":true,"language":"en-US","has_variations":true,"taxonomy_id":559,"taxonomy_path":["Clothing","Women's Clothing","Tops & Tees","T-shirts"],"used_manufacturer":false,"is_vintage":false},{"listing_id":829602042,"state":"active","user_id":190306416,"category_id":null,"title":"Live Love Laugh Zen Garden","description":"Take a quiet moment to reflect on what&#39;s truly important in your life and calm your senses. This beautiful Zen garden set features a tealight candle holder, light-colored sand, a small rake, and the largest rocks read &quot;Live&quot;, &quot;Laugh&quot; and &quot;Love&quot;. Tealight candle not included.\n\nWeight 2 pounds. 7.88&quot; x 6.25&quot; x 2.5&quot;. MDF Wood, Stone, Sand Plastic, Cement.","creation_tsz":1616710277,"ending_tsz":1627251077,"original_creation_tsz":1595529999,"last_modified_tsz":1616710277,"price":"32.00","currency_code":"USD","quantity":32,"sku":[],"tags":["home","decor","mdf wood","stone","sand","plastic","cement","zen","garden","tealight","light-colored","small rake","live laugh love"],"materials":[],"shop_section_id":27595403,"featured_rank":null,"state_tsz":1595529999,"url":"https:\/\/www.etsy.com\/listing\/829602042\/live-love-laugh-zen-garden?utm_source=thepuddinglistingima&utm_medium=api&utm_campaign=api","views":11,"num_favorers":0,"shipping_template_id":88975054823,"processing_min":1,"processing_max":3,"who_made":"i_did","is_supply":"false","when_made":"made_to_order","item_weight":null,"item_weight_unit":"oz","item_length":null,"item_width":null,"item_height":null,"item_dimensions_unit":"in","is_private":false,"recipient":null,"occasion":null,"style":null,"non_taxable":false,"is_customizable":true,"is_digital":false,"file_data":"","should_auto_renew":true,"language":"en-US","has_variations":false,"taxonomy_id":1110,"taxonomy_path":["Home & Living","Outdoor & Gardening","Garden Decoration"],"used_manufacturer":false,"is_vintage":false},{"listing_id":499601909,"state":"active","user_id":67326431,"category_id":null,"title":"Daughter Live, Laugh, Love Necklace - C129 - Gift for Daughter - Live Laugh Love Necklace - Personalized Gift for Daughter - Birthday Gift","description":"This elegant piece of jewelry will make a beautiful and sentimental gift that will best express your gratitude and love for your Daughter.\nPersonalized gifts magnify our thoughtful gesture;\n\nPlease CHOOSE the Gem Color from the drop down option.\n\nThis necklace includes:\n1 Daughter Charm\n1 Live Laugh Love Charm\n1 Personalized Gem Charm\n18-inch .925 Silver Plated Snake Chain with Lobster Clasp\n1 Gift Box with enclosed Card - Ready for Gift Giving\n(Gift Box will be wrapped with ribbon)\n\nCard Says:\nYour smile makes me smile, your laugh is infectious, your heart is pure and true; above all, I love that you are my daughter.\n\nThis necklace is presented with an elegant gift card cradled in a cotton-filled earth-tone kraft box, ready for gift giving.\n\nThe charms are made of lead-free, nickel-free antique silver Tibetan zinc alloy.\n\n****COUPON CODES****\n*Spend $50 at my shop and enjoy an additional 5% off your order (Coupon Code: FIVEPERCENT)\n*Spend $100 at my shop and enjoy an additional 10% off your order (Coupon Code: TENPERCENT)\n*Spend $150 at my shop and enjoy an additional 15% off your order (Coupon Code: FIFTEENPERCENT)\n*Complete all your shopping at Fairytale Endings Shop; the more you shop, the more you save!","creation_tsz":1616710260,"ending_tsz":1627251060,"original_creation_tsz":1481937881,"last_modified_tsz":1616710260,"price":"12.98","currency_code":"USD","quantity":48,"sku":[],"tags":["Live Laugh Love","Live Laugh Love Gift","Daughter Necklace","Daughter Gift","Gift for Daughter","Jewelry for Daughter","Mother Daughter","Gift from Mom","Daughter Jewelry","Personalized","Christmas Gift","Birthday Gift","Daughter"],"materials":["925 Silver Plated Snake Chain","Live Laugh Love Charm","Daughter Charm","Personalized Gem Charm"],"shop_section_id":20663503,"featured_rank":null,"state_tsz":1584715955,"url":"https:\/\/www.etsy.com\/listing\/499601909\/daughter-live-laugh-love-necklace-c129?utm_source=thepuddinglistingima&utm_medium=api&utm_campaign=api","views":92,"num_favorers":3,"shipping_template_id":31999040568,"processing_min":1,"processing_max":5,"who_made":"i_did","is_supply":"false","when_made":"made_to_order","item_weight":"2","item_weight_unit":"oz","item_length":"12","item_width":"10","item_height":"3","item_dimensions_unit":"in","is_private":false,"recipient":null,"occasion":null,"style":null,"non_taxable":false,"is_customizable":false,"is_digital":false,"file_data":"","should_auto_renew":true,"language":"en-US","has_variations":true,"taxonomy_id":1222,"taxonomy_path":["Jewelry","Necklaces","Charm Necklaces"],"used_manufacturer":false,"is_vintage":false},{"listing_id":714945833,"state":"active","user_id":140770012,"category_id":null,"title":"Live Laugh Love | Art Print","description":"Always remember to live, love and laugh \ud83c\udf3c\ud83d\udc9e\ud83e\udd23\n\nThis is an unframed print","creation_tsz":1616708454,"ending_tsz":1627249254,"original_creation_tsz":1560824777,"last_modified_tsz":1617897561,"price":"10.00","currency_code":"USD","quantity":20,"sku":[],"tags":["live love laugh sign","live love laugh","handmade","for sale","gifts","digital art","Columbus Ohio","art decor","decor","drawing","hanging art","home decor art","art for sale"],"materials":["Apple Pencil","procreate"],"shop_section_id":26540305,"featured_rank":2,"state_tsz":1617789281,"url":"https:\/\/www.etsy.com\/listing\/714945833\/live-laugh-love-art-print?utm_source=thepuddinglistingima&utm_medium=api&utm_campaign=api","views":37,"num_favorers":2,"shipping_template_id":null,"processing_min":1,"processing_max":2,"who_made":"i_did","is_supply":"false","when_made":"2020_2021","item_weight":"32","item_weight_unit":"oz","item_length":"20","item_width":"16","item_height":"1","item_dimensions_unit":"in","is_private":false,"recipient":null,"occasion":null,"style":null,"non_taxable":false,"is_customizable":false,"is_digital":false,"file_data":"","should_auto_renew":true,"language":"en-US","has_variations":true,"taxonomy_id":77,"taxonomy_path":["Art & Collectibles","Drawing & Illustration","Digital"],"used_manufacturer":false,"is_vintage":false},{"listing_id":587082260,"state":"active","user_id":23334942,"category_id":null,"title":"Live, Love, Laugh Charm Sterling Silver 14mm, silver Words Charms, Sterling Silver Charms, Live charms, Love charms, Laugh charms - SP383","description":"Beautiful Live, Love, Laugh charm.  Casted with 925 Sterling Silver in USA.\n\n0.7 inch high.\n\n14mm x 17.5mm\n\nWe offer this charm with different attachments at the top. Based on your requirements, please choose one from the drop down options, All attachments are sterling silver.\n\n1. With Jumpring, this is best if you are using it as a pendant on a neck chain.\n\n2. With springring clasp, this is best suited for charm bracelets.\n\n3. With lobster claw clasps,  this works if you want to attach to any thing with a loop or jumpring.\n\n4. With Large\/Big Hole beads, this makes the charm as a charm bead for European bracelets like Pandora, Camila etc.\n\n5. With 16 Inch Sterling silver 1.5mm Flat cable Chain with Spring Ring Closure.\n\n6. With 18 Inch Sterling silver 1.5mm Flat cable Chain with Spring Ring Closure.\n\n7. No attachment, charm only.\n\nFor option number 4, please mention which bead you would like.\n\nSee all my sterling silver charms\nhttps:\/\/www.etsy.com\/your\/listings?shipping_profile_id=&search_query=sterling+silver+charms","creation_tsz":1616708237,"ending_tsz":1627249037,"original_creation_tsz":1521208506,"last_modified_tsz":1616708237,"price":"3.20","currency_code":"USD","quantity":7,"sku":["SP383-SRC","SP383-SF118","SP383-SCHFC161","SP383-SCHFC181","SP383","SP383-SJRO5","SP383-LHB"],"tags":["silver charms","bead prism","925 Silver Charm","charm beads","love charms","live charms","laugh charms","live love laugh cham","words charms","Message Charms","Inspirational Charms","clip on charms"],"materials":["925 Sterling Silver","Made in USA","Convo for Larger quantities","Sterling Silver","See Last Picture for attachments","14mm","Read Description"],"shop_section_id":13225485,"featured_rank":null,"state_tsz":1615818896,"url":"https:\/\/www.etsy.com\/listing\/587082260\/live-love-laugh-charm-sterling-silver?utm_source=thepuddinglistingima&utm_medium=api&utm_campaign=api","views":32,"num_favorers":5,"shipping_template_id":177436704,"processing_min":1,"processing_max":3,"who_made":"someone_else","is_supply":"true","when_made":"2020_2021","item_weight":null,"item_weight_unit":"oz","item_length":null,"item_width":null,"item_height":null,"item_dimensions_unit":"in","is_private":false,"recipient":"teen_girls","occasion":null,"style":null,"non_taxable":false,"is_customizable":false,"is_digital":false,"file_data":"","should_auto_renew":true,"language":"en-US","has_variations":true,"taxonomy_id":6426,"taxonomy_path":["Craft Supplies & Tools","Beads, Gems & Cabochons","Charms & Pendants","Charms"],"used_manufacturer":false,"is_vintage":false},{"listing_id":882035873,"state":"active","user_id":220794857,"category_id":null,"title":"Pewter Spacer Beads, Message Beads  &quot;Joy&quot;, 1.3mm hole, 8in Strand","description":"\u2022 Pewter Spacer Bead\n\n\u2022 L 12mm x W 2mm\n\n\u2022 Hole: 1.3mm\n\n\u2022\u00a0 ~16 pcs per strand \n\n\u2022 8 Inch Strand \n\n\u2022 Lead Free\/Nickle Free\n\n\u2022 SKU: 100265","creation_tsz":1616707269,"ending_tsz":1627248069,"original_creation_tsz":1601927943,"last_modified_tsz":1616707269,"price":"5.00","currency_code":"USD","quantity":17,"sku":["100265"],"tags":["Metal Beads","Pewter","Spacers","Live laugh love","Message Beads","beaded jewelry","jewelry making beads","Beading"],"materials":["Pewter"],"shop_section_id":28415520,"featured_rank":null,"state_tsz":1601927943,"url":"https:\/\/www.etsy.com\/listing\/882035873\/pewter-spacer-beads-message-beads-joy?utm_source=thepuddinglistingima&utm_medium=api&utm_campaign=api","views":16,"num_favorers":3,"shipping_template_id":74735427259,"processing_min":1,"processing_max":3,"who_made":"someone_else","is_supply":"true","when_made":"2010_2019","item_weight":null,"item_weight_unit":null,"item_length":null,"item_width":null,"item_height":null,"item_dimensions_unit":null,"is_private":false,"recipient":null,"occasion":null,"style":null,"non_taxable":true,"is_customizable":false,"is_digital":false,"file_data":"","should_auto_renew":true,"language":"en-US","has_variations":false,"taxonomy_id":6238,"taxonomy_path":["Craft Supplies & Tools","Beads, Gems & Cabochons","Beads"],"used_manufacturer":false,"is_vintage":false},{"listing_id":897346116,"state":"active","user_id":101376053,"category_id":null,"title":"Love is the new black white coffee mug | Gift for friends and Family| Holiday present| 11 Oz 15 Oz  coffee cup | Made in USA | Inspirational","description":"- High quality mug makes the perfect gift for everyone.\n - Printed on only the highest quality mugs. The print will never fade no matter how many times it is washed.\n - Packaged, and shipped from the USA.\n - Dishwasher and Microwave safe.\n - Shipped in a custom made styrofoam package to ensure it arrives perfect. GUARANTEED.","creation_tsz":1616707235,"ending_tsz":1627248035,"original_creation_tsz":1606254259,"last_modified_tsz":1616707235,"price":"15.95","currency_code":"USD","quantity":999,"sku":["17-White","16-White"],"tags":["love mug","friendship mug","i love you gift","present for mom","family gift","unique coffee mug","mugs you are loved","love is new black","gift for sister","live laugh love mug","gift for grandma","mom gifts","coffee mug designs"],"materials":["Ceramic","Porcelain"],"shop_section_id":null,"featured_rank":null,"state_tsz":1616386997,"url":"https:\/\/www.etsy.com\/listing\/897346116\/love-is-the-new-black-white-coffee-mug?utm_source=thepuddinglistingima&utm_medium=api&utm_campaign=api","views":7,"num_favorers":0,"shipping_template_id":62344503606,"processing_min":5,"processing_max":10,"who_made":"someone_else","is_supply":"false","when_made":"made_to_order","item_weight":null,"item_weight_unit":"oz","item_length":null,"item_width":null,"item_height":null,"item_dimensions_unit":"in","is_private":false,"recipient":null,"occasion":null,"style":null,"non_taxable":false,"is_customizable":false,"is_digital":false,"file_data":"","should_auto_renew":true,"language":"en-US","has_variations":true,"taxonomy_id":1062,"taxonomy_path":["Home & Living","Kitchen & Dining","Drink & Barware","Drinkware","Mugs"],"used_manufacturer":false,"is_vintage":false}],"params":{"limit":25,"offset":0,"page":"99","keywords":null,"sort_on":"created","sort_order":"down","min_price":null,"max_price":null,"color":null,"color_accuracy":0,"tags":"live laugh love","taxonomy_id":null,"location":null,"lat":null,"lon":null,"region":null,"geo_level":"city","accepts_gift_cards":"false","translate_keywords":"false"},"type":"Listing","pagination":{"effective_limit":25,"effective_offset":2450,"next_offset":2475,"effective_page":99,"next_page":100}}